cdk_s3bucket_ng/__init__.py
cdk_s3bucket_ng/py.typed
cdk_s3bucket_ng/_jsii/__init__.py
cdk_s3bucket_ng/_jsii/cdk-s3bucket-ng@2.0.184.jsii.tgz
cdk_s3bucket_ng-2.0.184.dist-info/LICENSE
cdk_s3bucket_ng-2.0.184.dist-info/METADATA
cdk_s3bucket_ng-2.0.184.dist-info/WHEEL
cdk_s3bucket_ng-2.0.184.dist-info/top_level.txt
cdk_s3bucket_ng-2.0.184.dist-info/RECORD
